Workbook
Name SegmentaçãodeDados_dia: #N/A
Name Usuario: #REF!

Sheet TD Painel
M2: Ano | N2: 2026 | R2: DiretoriaComercial | S2: DIRETORIA SPI
C3: ano | D3: 2026 | M3: canal_loja | N3: HOUSE | R3: Ano | S3: 2026
C4: nom_empreendimento | D4: All | M4: loja_ags | N4: NÃO
C5: diretoria | D5: DIRETORIA SPI | R5: DataBaseAssinaturaContratoSalesforce | S5: NomeGerente | T5: NomeCorretor | U5: NomeLoja | V5: NomeImobiliaria | W5: # Vendas
C6: dia | D6: All | M6: DataBase | N6: regional_co | O6: nom_gerente | P6: TotalCorretores | Q6: TotalCorretoresMais10DiasSemLogin | R6: jan/2026 | T6: RAFAEL FERNANDES DECHICHI | U6: AGENTE DE SONHOS – EXTERIOR (NP 1) | W6: 3
M7: 01/01/2026 | N7: SENSIA CP | O7: IDELSO JOSE DA SILVA SANTOS DE ASSIS | P7: 19 | Q7: 15 | R7: jan/2026 | T7: WELLINGHTON CESAR PEREIRA FIGUEIREDO | U7: SENSIA IMOB CAMPINAS | V7: M.L.N DE CASTRO CARVALHO | W7: 1
C8: data_base | D8: canal_loja | E8: gerente | F8: supervisor_imob | G8: nom_corretor | H8: nom_imobiliaria | I8: status_funil | J8: regional | K8: Funil_Real | M8: 01/01/2026 | N8: SENSIA RP | O8: DOUGLAS MENDES DE AGUIAR RODRIGUES | P8: 12 | Q8: 8 | R8: jan/2026 | T8: WELLINGHTON CESAR PEREIRA FIGUEIREDO | U8: SENSIA IMOB CAMPINAS | V8: RE IMOBILIARIA EIRELI EPP | W8: 5
C9: 01/06/2026 | D9: AGS | G9: ANA RAQUEL CANDIDO MARCHETI | I9: LEAD | J9: SP INT 3 | K9: 24 | M9: 01/01/2026 | N9: SP INT 1 | O9: ANDERSON COSTA CARAPETA | P9: 13 | Q9: 6 | R9: jan/2026 | T9: WELLINGHTON CESAR PEREIRA FIGUEIREDO | U9: SENSIA IMOB CAMPINAS | V9: SATUS NEGOCIOS IMOBILIARIOS LTDA | W9: 2
C10: 01/06/2026 | D10: AGS | G10: ANNA CAROLINA REIS DECHICHI | I10: DOCUMENTAÇÃO ENVIADA | J10: SP INT 4 | K10: 18 | M10: 01/01/2026 | N10: SP INT 1 | O10: EVANDRO DE BRITO | P10: 16 | Q10: 7 | R10: jan/2026 | T10: WELLINGHTON CESAR PEREIRA FIGUEIREDO | U10: SENSIA IMOB CAMPINAS | V10: TASSELLI ADM E SERVIÇÕS IMOBILIARIOS LTDA CAMPINAS IMOB | W10: 1
C11: 01/06/2026 | D11: AGS | G11: ANNA CAROLINA REIS DECHICHI | I11: DOCUMENTAÇÃO EM ANÁLISE | J11: SP INT 4 | K11: 18 | M11: 01/01/2026 | N11: SP INT 1 | O11: FABIO HENRIQUE VIDOTTI FERREIRA | P11: 2 | R11: jan/2026 | S11: ADALTON JOSE DA SILVA | T11: AUDILAINE SANTANA DE SOUZA | U11: LOJA EQUIPE VIRTUAL BOTUCATU 1 | W11: 1
C12: 01/06/2026 | D12: AGS | G12: ANNA CAROLINA REIS DECHICHI | I12: CPF ANALISADO | J12: SP INT 4 | K12: 18 | M12: 01/01/2026 | N12: SP INT 1 | O12: PABLO MEDEIROS DA SILVA GADELHA | P12: 17 | Q12: 13 | R12: jan/2026 | S12: ADALTON JOSE DA SILVA | T12: CLEIDE APARECIDA RIBEIRA DA SILVA | U12: LOJA EQUIPE VIRTUAL BOTUCATU 1 | W12: 1
C13: 01/06/2026 | D13: AGS | G13: ANNA CAROLINA REIS DECHICHI | I13: CPF APROVADO | J13: SP INT 4 | K13: 16 | M13: 01/01/2026 | N13: SP INT 1 | O13: THAINA PIOLOGO MARQUES DE QUEIROZ | P13: 1 | R13: jan/2026 | S13: ADALTON JOSE DA SILVA | T13: CLEITON FRANCISCO XAVIER | U13: LOJA EQUIPE VIRTUAL BOTUCATU 1 | W13: 2
C14: 01/06/2026 | D14: AGS | G14: ANNA CAROLINA REIS DECHICHI | I14: CPF CONDICIONADO | J14: SP INT 4 | K14: 2 | M14: 01/01/2026 | N14: SP INT 1 | O14: THAMIRES PEREIRA COSTA | P14: 18 | Q14: 5 | R14: jan/2026 | S14: ADALTON JOSE DA SILVA | T14: ISABELA CAROLINE LEMES | U14: LOJA EQUIPE VIRTUAL BOTUCATU 1 | W14: 1
C15: 01/06/2026 | D15: AGS | G15: ANNA CAROLINA REIS DECHICHI | I15: CONTRATO GERADO | J15: SP INT 4 | K15: 23 | M15: 01/01/2026 | N15: SP INT 1 | O15: TIAGO AUGUSTO DA COSTA | P15: 17 | Q15: 5 | R15: jan/2026 | S15: ADALTON JOSE DA SILVA | T15: JEAN CARLOS DE OLIVEIRA GOMES | U15: LOJA EQUIPE VIRTUAL BOTUCATU 1 | W15: 1
C16: 01/06/2026 | D16: AGS | G16: ANNA CAROLINA REIS DECHICHI | I16: CONTRATO ASSINADO | J16: SP INT 4 | K16: 11 | M16: 01/01/2026 | N16: SP INT 2 | O16: DOMINIQUE DAMASO DE SALES | P16: 14 | Q16: 9 | R16: jan/2026 | S16: ADALTON JOSE DA SILVA | T16: JOAO PAULO CAVAZZANA | U16: LOJA EQUIPE VIRTUAL BOTUCATU 1 | W16: 1
C17: 01/06/2026 | D17: AGS | G17: ANNA CAROLINA REIS DECHICHI | I17: GANHO | J17: SP INT 4 | K17: 12 | M17: 01/01/2026 | N17: SP INT 2 | O17: FLAVIANO DE SOUZA CORREA | P17: 15 | Q17: 6 | R17: jan/2026 | S17: ADALTON JOSE DA SILVA | T17: MARCOS ANTÔNIO GARCIA | U17: LOJA EQUIPE VIRTUAL BOTUCATU 1 | W17: 2
C18: 01/06/2026 | D18: AGS | G18: BRUNO PEREIRA SANTOS | I18: LEAD | J18: SP INT 4 | K18: 121 | M18: 01/01/2026 | N18: SP INT 2 | O18: HEITOR NEVES MANCUZO | P18: 19 | Q18: 10 | R18: jan/2026 | S18: ADALTON JOSE DA SILVA | T18: ROSANGELA APARECIDA PINTO SIMÃO | U18: LOJA EQUIPE VIRTUAL BOTUCATU 1 | W18: 1
C19: 01/06/2026 | D19: AGS | G19: BRUNO PEREIRA SANTOS | I19: DOCUMENTAÇÃO ENVIADA | J19: SP INT 4 | K19: 3 | M19: 01/01/2026 | N19: SP INT 2 | O19: RAFAEL MOLL RECUPERO | P19: 12 | Q19: 8 | R19: jan/2026 | S19: ADALTON JOSE DA SILVA | T19: SOLENE MATOS DE AQUINO | U19: LOJA EQUIPE VIRTUAL BOTUCATU 1 | W19: 1
C20: 01/06/2026 | D20: AGS | G20: BRUNO PEREIRA SANTOS | I20: DOCUMENTAÇÃO EM ANÁLISE | J20: SP INT 4 | K20: 3 | M20: 01/01/2026 | N20: SP INT 2 | O20: STEPHANE MASCARENHAS TEIXEIRA | P20: 13 | Q20: 12 | R20: jan/2026 | S20: ALEXANDRE FORMIGA NETO | T20: LEONARDO VICTOR DA SILVA | U20: EQUIPE CREDENCIADA JUNDIAI 2 | W20: 1
C21: 01/06/2026 | D21: AGS | G21: BRUNO PEREIRA SANTOS | I21: CPF ANALISADO | J21: SP INT 4 | K21: 3 | M21: 01/01/2026 | N21: SP INT 3 | O21: ARMANDO DONIZETTI CUSTODIO | P21: 16 | Q21: 12 | R21: jan/2026 | S21: ALEXANDRE FORMIGA NETO | T21: LUCIANA AMARAL ARAÚJO QUINTAL | U21: EQUIPE CREDENCIADA JUNDIAI 2 | W21: 2
C22: 01/06/2026 | D22: AGS | G22: BRUNO PEREIRA SANTOS | I22: CPF APROVADO | J22: SP INT 4 | K22: 3 | M22: 01/01/2026 | N22: SP INT 3 | O22: BRUNA PAULINO BENEDETTI | P22: 8 | Q22: 7 | R22: jan/2026 | S22: ALEXANDRE FORMIGA NETO | T22: PAULO ALEXANDRE JORGE | U22: EQUIPE CREDENCIADA JUNDIAI 2 | W22: 2
C23: 01/06/2026 | D23: AGS | G23: BRUNO PEREIRA SANTOS | I23: CONTRATO GERADO | J23: SP INT 4 | K23: 6 | M23: 01/01/2026 | N23: SP INT 3 | O23: DEIVES RODRIGO DA COSTA | P23: 17 | Q23: 10 | R23: jan/2026 | S23: ALEXANDRE FORMIGA NETO | T23: RUTH NUNES DOS SANTOS LIMA | U23: EQUIPE CREDENCIADA JUNDIAI 2 | W23: 1
C24: 01/06/2026 | D24: AGS | G24: BRUNO PEREIRA SANTOS | I24: CONTRATO ASSINADO | J24: SP INT 4 | K24: 3 | M24: 01/01/2026 | N24: SP INT 3 | O24: MAISA MUNIZ DA SILVA | P24: 7 | Q24: 2 | R24: jan/2026 | S24: ALINE CRISTINA MORENO | T24: ALANA EMILY DE SOUZA BATISTA | U24: IMOB CAMPINAS 2 | V24: KC CONCEITO IMOBILIARIO LTDA | W24: 1
C25: 01/06/2026 | D25: AGS | G25: BRUNO PEREIRA SANTOS | I25: GANHO | J25: SP INT 4 | K25: 2 | M25: 01/01/2026 | N25: SP INT 3 | O25: PEDRO MORENO MARQUES | P25: 13 | Q25: 7 | R25: jan/2026 | S25: ALINE CRISTINA MORENO | T25: GUSTAVO GUINATTI VENTURINI | U25: IMOB CAMPINAS 1 | V25: CARVALHO E CARVALHO CORRETAGEM DE IMÓVEIS | W25: 1
C26: 01/06/2026 | D26: AGS | G26: ELISABETE DE MORAES BOTELHO | I26: DOCUMENTAÇÃO ENVIADA | J26: SP INT 3 | K26: 1 | M26: 01/01/2026 | N26: SP INT 3 | O26: RAFAEL DOS SANTOS NOGUEIRA | P26: 1 | Q26: 1 | R26: jan/2026 | S26: ALINE CRISTINA MORENO | T26: GUSTAVO GUINATTI VENTURINI | U26: IMOB CAMPINAS 1 | V26: HUBIMOB | W26: 2
C27: 01/06/2026 | D27: AGS | G27: ELISABETE DE MORAES BOTELHO | I27: DOCUMENTAÇÃO EM ANÁLISE | J27: SP INT 3 | K27: 1 | M27: 01/01/2026 | N27: SP INT 3 | O27: THAYNA LAIS DA SILVA | P27: 13 | Q27: 9 | R27: jan/2026 | S27: ALINE CRISTINA MORENO | T27: GUSTAVO GUINATTI VENTURINI | U27: IMOB CAMPINAS 1 | V27: IMBATIVEIS IMOVEIS | W27: 1
C28: 01/06/2026 | D28: AGS | G28: ELISABETE DE MORAES BOTELHO | I28: CPF ANALISADO | J28: SP INT 3 | K28: 1 | M28: 01/01/2026 | N28: SP INT 4 | O28: ADALTON JOSE DA SILVA | P28: 12 | Q28: 3 | R28: jan/2026 | S28: ALINE CRISTINA MORENO | T28: GUSTAVO GUINATTI VENTURINI | U28: IMOB CAMPINAS 1 | V28: MICHEL CASTRO LOPES AGENTE IMOBILIARIO ME | W28: 1
C29: 01/06/2026 | D29: AGS | G29: ELISABETE DE MORAES BOTELHO | I29: CPF APROVADO | J29: SP INT 3 | K29: 1 | M29: 01/01/2026 | N29: SP INT 4 | O29: DAIANE CRISTINA JIRICO | P29: 21 | Q29: 14 | R29: jan/2026 | S29: ALINE CRISTINA MORENO | T29: GUSTAVO GUINATTI VENTURINI | U29: IMOB CAMPINAS 1 | V29: NISHIDA NEGOCIOS IMOBILIARIOS | W29: 3
C30: 01/06/2026 | D30: AGS | G30: ELTON APARECIDO DA SILVA NOGUEIRA | I30: LEAD | J30: SP INT 3 | K30: 1 | M30: 01/01/2026 | N30: SP INT 4 | O30: GUSTAVO MACHADO TENORIO | P30: 14 | Q30: 8 | R30: jan/2026 | S30: ALINE CRISTINA MORENO | T30: GUSTAVO GUINATTI VENTURINI | U30: IMOB CAMPINAS 1 | V30: RE IMOBILIARIA EIRELI EPP | W30: 1
C31: 01/06/2026 | D31: AGS | G31: ELTON APARECIDO DA SILVA NOGUEIRA | I31: DOCUMENTAÇÃO ENVIADA | J31: SP INT 3 | K31: 1 | M31: 01/01/2026 | N31: SP INT 4 | O31: JAYRANE CAROLINE MARTINS FERRARI | P31: 20 | Q31: 9 | R31: jan/2026 | S31: ALINE CRISTINA MORENO | T31: GUSTAVO GUINATTI VENTURINI | U31: IMOB CAMPINAS 1 | V31: TK ASSESSORIA IMOBILIARIA | W31: 1
C32: 01/06/2026 | D32: AGS | G32: ELTON APARECIDO DA SILVA NOGUEIRA | I32: DOCUMENTAÇÃO COM PENDÊNCIA | J32: SP INT 3 | K32: 1 | M32: 01/01/2026 | N32: SP INT 4 | O32: JULIANO MARQUES VALENTE | P32: 2 | Q32: 1 | R32: jan/2026 | S32: ALINE CRISTINA MORENO | T32: LARISSA NEVES TEIXEIRA | U32: IMOB CAMPINAS 3 | V32: BLACK NEGOCIOS IMOBILIARIOS LTDA | W32: 1
C33: 01/06/2026 | D33: AGS | G33: FLAVIA DA COSTA LUIZ | I33: LEAD | J33: SP INT 4 | K33: 197 | M33: 01/01/2026 | N33: SP INT 4 | O33: REBECA PEREIRA BONFIM DA SILVA | P33: 3 | Q33: 3 | R33: jan/2026 | S33: ALINE CRISTINA MORENO | T33: LARISSA NEVES TEIXEIRA | U33: IMOB CAMPINAS 3 | V33: CASA BROKER NEGOCIOS IMOBILIARIOS LTDA | W33: 1
C34: 01/06/2026 | D34: AGS | G34: FLAVIA DA COSTA LUIZ | I34: DOCUMENTAÇÃO ENVIADA | J34: SP INT 4 | K34: 6 | M34: 01/01/2026 | N34: SP INT 4 | O34: TIAGO ALVES CARVALHO COELHO | P34: 17 | Q34: 7 | R34: jan/2026 | S34: ALINE CRISTINA MORENO | T34: LARISSA NEVES TEIXEIRA | U34: IMOB CAMPINAS 3 | V34: HUBIMOB | W34: 4
C35: 01/06/2026 | D35: AGS | G35: FLAVIA DA COSTA LUIZ | I35: DOCUMENTAÇÃO EM ANÁLISE | J35: SP INT 4 | K35: 5 | M35: 01/01/2026 | N35: SP INT 5 | O35: JEFERSON EDUARDO NUNES | P35: 17 | Q35: 14 | R35: jan/2026 | S35: ALINE CRISTINA MORENO | T35: LARISSA NEVES TEIXEIRA | U35: IMOB CAMPINAS 3 | V35: MICHEL CASTRO LOPES AGENTE IMOBILIARIO ME | W35: 1
... C46: 01/06/2026 | D46: AGS | G46: JOAO MOYSES JUNIOR | I46: CPF CONDICIONADO | J46: SP INT 3 | K46: 1 | M46: 01/02/2026 | N46: SENSIA RP | O46: DOUGLAS MENDES DE AGUIAR RODRIGUES | P46: 17 | Q46: 10 | R46: jan/2026 | S46: ANA RAQUEL CANDIDO MARCHETI | T46: CAMILA MENDES FRANCISCO | U46: LOJA IMOB PIRACICABA | V46: BELLA IMOVEIS BRASIL | W46: 1
C47: 01/06/2026 | D47: AGS | G47: JOSE SOARES DA COSTA | I47: CONTRATO ASSINADO | J47: SP INT 3 | K47: 1 | M47: 01/02/2026 | N47: SP INT 1 | P47: 8 | Q47: 3 | R47: jan/2026 | S47: ANA RAQUEL CANDIDO MARCHETI | T47: CAMILA MENDES FRANCISCO | U47: LOJA IMOB PIRACICABA | V47: CONECTA GESTAO IMOBILIARIA | W47: 1
C48: 01/06/2026 | D48: AGS | G48: JOSE SOARES DA COSTA | I48: GANHO | J48: SP INT 3 | K48: 1 | M48: 01/02/2026 | N48: SP INT 1 | O48: ALEXANDRE MIRANDA DOS PASSOS | P48: 2 | Q48: 2 | R48: jan/2026 | S48: ANA RAQUEL CANDIDO MARCHETI | T48: CAMILA MENDES FRANCISCO | U48: LOJA IMOB PIRACICABA | V48: H12 CONSULTORIA IMOBILIARIA LTDA | W48: 1
C49: 01/06/2026 | D49: AGS | G49: JOSÉ SOARES DA COSTA | I49: LEAD | J49: SP INT 3 | K49: 1 | M49: 01/02/2026 | N49: SP INT 1 | O49: ANDERSON COSTA CARAPETA | P49: 18 | Q49: 9 | R49: jan/2026 | S49: ANA RAQUEL CANDIDO MARCHETI | T49: CAMILA MENDES FRANCISCO | U49: LOJA IMOB PIRACICABA | V49: IMOBILIARIA SANTOS | W49: 1
C50: 01/06/2026 | D50: AGS | G50: JOSÉ SOARES DA COSTA | I50: DOCUMENTAÇÃO ENVIADA | J50: SP INT 3 | K50: 5 | M50: 01/02/2026 | N50: SP INT 1 | O50: EVANDRO DE BRITO | P50: 18 | Q50: 9 | R50: jan/2026 | S50: ANA RAQUEL CANDIDO MARCHETI | T50: CAMILA MENDES FRANCISCO | U50: LOJA IMOB PIRACICABA | V50: INLOCUS IMOVEIS | W50: 2
C51: 01/06/2026 | D51: AGS | G51: JOSÉ SOARES DA COSTA | I51: DOCUMENTAÇÃO EM ANÁLISE | J51: SP INT 3 | K51: 2 | M51: 01/02/2026 | N51: SP INT 1 | O51: FABIO HENRIQUE VIDOTTI FERREIRA | P51: 4 | Q51: 2 | R51: jan/2026 | S51: ANA RAQUEL CANDIDO MARCHETI | T51: CAMILA MENDES FRANCISCO | U51: LOJA IMOB PIRACICABA | V51: INNOVA HOUSE | W51: 1
C52: 01/06/2026 | D52: AGS | G52: JOSÉ SOARES DA COSTA | I52: DOCUMENTAÇÃO COM PENDÊNCIA | J52: SP INT 3 | K52: 3 | M52: 01/02/2026 | N52: SP INT 1 | O52: PABLO MEDEIROS DA SILVA GADELHA | P52: 20 | Q52: 15 | R52: jan/2026 | S52: ANA RAQUEL CANDIDO MARCHETI | T52: CAMILA MENDES FRANCISCO | U52: LOJA IMOB PIRACICABA | V52: J MOREIRA DOS SANTOS IMOVEIS | W52: 2
C53: 01/06/2026 | D53: AGS | G53: JOSÉ SOARES DA COSTA | I53: CPF ANALISADO | J53: SP INT 3 | K53: 2 | M53: 01/02/2026 | N53: SP INT 1 | O53: THAMIRES PEREIRA COSTA | P53: 18 | Q53: 5 | R53: jan/2026 | S53: ANA RAQUEL CANDIDO MARCHETI | T53: CAMILA MENDES FRANCISCO | U53: LOJA IMOB PIRACICABA | V53: LIMA FORTINI GESTAO IMOBILIARIA | W53: 1
C54: 01/06/2026 | D54: AGS | G54: JOSÉ SOARES DA COSTA | I54: CPF ANALISADO COM PENDÊNCIA | J54: SP INT 3 | K54: 1 | M54: 01/02/2026 | N54: SP INT 1 | O54: TIAGO AUGUSTO DA COSTA | P54: 17 | Q54: 5 | R54: jan/2026 | S54: ANA RAQUEL CANDIDO MARCHETI | T54: CAMILA MENDES FRANCISCO | U54: LOJA IMOB PIRACICABA | V54: PREMIER INTELIGENCIA IMOBILIARIA | W54: 1
C55: 01/06/2026 | D55: AGS | G55: JOSÉ SOARES DA COSTA | I55: CPF APROVADO | J55: SP INT 3 | K55: 1 | M55: 01/02/2026 | N55: SP INT 2 | P55: 8 | Q55: 4 | R55: jan/2026 | S55: ANA RAQUEL CANDIDO MARCHETI | T55: CAMILA MENDES FRANCISCO | U55: LOJA IMOB PIRACICABA | V55: TRIADE SOLUCOES IMOBILIARIAS | W55: 2
C56: 01/06/2026 | D56: AGS | G56: JOSÉ SOARES DA COSTA | I56: CPF CONDICIONADO | J56: SP INT 3 | K56: 1 | M56: 01/02/2026 | N56: SP INT 2 | O56: DOMINIQUE DAMASO DE SALES | P56: 16 | Q56: 10 | R56: jan/2026 | S56: ANA RAQUEL CANDIDO MARCHETI | T56: LUCIANO FERREIRA DA SILVA | U56: LOJA IMOB LIMEIRA 2 | V56: DAMA SOLUCOES IMOBILIARIAS | W56: 11
C57: 01/06/2026 | D57: AGS | G57: JOSÉ SOARES DA COSTA | I57: CPF CONDICIONADO COM PENDÊNCIA | J57: SP INT 3 | K57: 1 | M57: 01/02/2026 | N57: SP INT 2 | O57: FLAVIANO DE SOUZA CORREA | P57: 15 | Q57: 6 | R57: jan/2026 | S57: ANA RAQUEL CANDIDO MARCHETI | T57: LUCIANO FERREIRA DA SILVA | U57: LOJA IMOB LIMEIRA 2 | V57: IMOBILIARIA ZAFIRA | W57: 2
C58: 01/06/2026 | D58: AGS | G58: JOSÉ SOARES DA COSTA | I58: CONTRATO GERADO | J58: SP INT 3 | K58: 1 | M58: 01/02/2026 | N58: SP INT 2 | O58: HEITOR NEVES MANCUZO | P58: 21 | Q58: 10 | R58: jan/2026 | S58: ANA RAQUEL CANDIDO MARCHETI | T58: LUCIANO FERREIRA DA SILVA | U58: LOJA IMOB LIMEIRA 2 | V58: PERSONARE IMOVEIS | W58: 2
C59: 01/06/2026 | D59: AGS | G59: JOSIANE BRITO LAVANDOSKY | I59: DOCUMENTAÇÃO ENVIADA | J59: SP INT 3 | K59: 2 | M59: 01/02/2026 | N59: SP INT 2 | O59: RAFAEL MOLL RECUPERO | P59: 14 | Q59: 10 | R59: jan/2026 | S59: ANA RAQUEL CANDIDO MARCHETI | T59: LUCIANO FERREIRA DA SILVA | U59: LOJA IMOB LIMEIRA 2 | V59: RIBEIRO IMOVEIS LIMEIRA | W59: 1
C60: 01/06/2026 | D60: AGS | G60: JOSIANE BRITO LAVANDOSKY | I60: DOCUMENTAÇÃO EM ANÁLISE | J60: SP INT 3 | K60: 1 | M60: 01/02/2026 | N60: SP INT 2 | O60: STEPHANE MASCARENHAS TEIXEIRA | P60: 15 | Q60: 13 | R60: jan/2026 | S60: ANA RAQUEL CANDIDO MARCHETI | T60: LUCIANO FERREIRA DA SILVA | U60: LOJA IMOB LIMEIRA 2 | V60: VL NEGOCIOS IMOBILIARIOS LTDA | W60: 1
C61: 01/06/2026 | D61: AGS | G61: JOSIANE BRITO LAVANDOSKY | I61: DOCUMENTAÇÃO COM PENDÊNCIA | J61: SP INT 3 | K61: 1 | M61: 01/02/2026 | N61: SP INT 3 | O61: ARMANDO DONIZETTI CUSTODIO | P61: 16 | Q61: 13 | R61: jan/2026 | S61: ANA RAQUEL CANDIDO MARCHETI | T61: RODRIGO PEREIRA DE ALMEIDA | U61: LOJA IMOB SBO | V61: ALTERNATIVE HOUSE NEGOCIOS IMOBILIARIOS | W61: 2
C62: 01/06/2026 | D62: AGS | G62: JOSIANE BRITO LAVANDOSKY | I62: CPF ANALISADO | J62: SP INT 3 | K62: 1 | M62: 01/02/2026 | N62: SP INT 3 | O62: BRUNA PAULINO BENEDETTI | P62: 9 | Q62: 7 | R62: jan/2026 | S62: ANA RAQUEL CANDIDO MARCHETI | T62: WANDERSON FERNANDO ALVES JUNIOR | U62: LOJA IMOB LIMEIRA | V62: LUDUGERIO E ANDRADE CORRETAGEM DE IMOVEIS LTDA | W62: 1
C63: 01/06/2026 | D63: AGS | G63: JOSIANE BRITO LAVANDOSKY | I63: CPF CONDICIONADO | J63: SP INT 3 | K63: 1 | M63: 01/02/2026 | N63: SP INT 3 | O63: DEIVES RODRIGO DA COSTA | P63: 23 | Q63: 14 | R63: jan/2026 | S63: ANA RAQUEL CANDIDO MARCHETI | T63: WANDERSON FERNANDO ALVES JUNIOR | U63: LOJA IMOB LIMEIRA | V63: NOVA DEFINE | W63: 2
C64: 01/06/2026 | D64: AGS | G64: JOSIANE BRITO LAVANDOSKY | I64: CONTRATO GERADO | J64: SP INT 3 | K64: 1 | M64: 01/02/2026 | N64: SP INT 3 | O64: MAISA MUNIZ DA SILVA | P64: 9 | Q64: 4 | R64: jan/2026 | S64: ANA RAQUEL CANDIDO MARCHETI | T64: WANDERSON FERNANDO ALVES JUNIOR | U64: LOJA IMOB LIMEIRA | V64: PERFECT NEGOCIOS IMOBILIARIOS | W64: 7
C65: 01/06/2026 | D65: AGS | G65: JOSIANE BRITO LAVANDOSKY | I65: CONTRATO ASSINADO | J65: SP INT 3 | K65: 1 | M65: 01/02/2026 | N65: SP INT 3 | O65: PEDRO MORENO MARQUES | P65: 14 | Q65: 7 | R65: jan/2026 | S65: ANA RAQUEL CANDIDO MARCHETI | T65: WANDERSON FERNANDO ALVES JUNIOR | U65: LOJA IMOB LIMEIRA | V65: SOMA IMOVEIS LIMEIRA | W65: 5
C66: 01/06/2026 | D66: AGS | G66: JOSIANE BRITO LAVANDOSKY | I66: GANHO | J66: SP INT 3 | K66: 1 | M66: 01/02/2026 | N66: SP INT 3 | O66: RAFAEL DOS SANTOS NOGUEIRA | P66: 1 | Q66: 1 | R66: jan/2026 | S66: ANDERSON COSTA CARAPETA | T66: ANGELICA NASCIMENTO DA SILVA | U66: VIRTUAL CPS 3 | W66: 2
C67: 01/06/2026 | D67: AGS | G67: KARINE LARESCA MEIRELES PERES | I67: LEAD | J67: SP INT 4 | K67: 8 | M67: 01/02/2026 | N67: SP INT 3 | O67: THAYNA LAIS DA SILVA | P67: 13 | Q67: 9 | R67: jan/2026 | S67: ANDERSON COSTA CARAPETA | T67: ISA DO CARMO VENANCIO | U67: VIRTUAL CPS 3 | W67: 1
C68: 01/06/2026 | D68: AGS | G68: KATIA ALESSANDRA MENEZES SILVA | I68: LEAD | J68: SP INT 1 | K68: 1 | M68: 01/02/2026 | N68: SP INT 4 | O68: ADALTON JOSE DA SILVA | P68: 15 | Q68: 5 | R68: jan/2026 | S68: ANDERSON COSTA CARAPETA | T68: JOÃO RICARDO TRECCO | U68: VIRTUAL CPS 3 | W68: 1
C69: 01/06/2026 | D69: AGS | G69: LUCYARA SIQUEIRA | I69: LEAD | J69: SP INT 4 | K69: 8 | M69: 01/02/2026 | N69: SP INT 4 | O69: DAIANE CRISTINA JIRICO | P69: 25 | Q69: 18 | R69: jan/2026 | S69: ANDERSON COSTA CARAPETA | T69: LORRAMÍ SILVA DOS SANTOS | U69: VIRTUAL CPS 3 | W69: 2
C70: 01/06/2026 | D70: AGS | G70: LUCYARA SIQUEIRA | I70: DOCUMENTAÇÃO ENVIADA | J70: SP INT 4 | K70: 3 | M70: 01/02/2026 | N70: SP INT 4 | O70: GUSTAVO MACHADO TENORIO | P70: 15 | Q70: 9 | R70: jan/2026 | S70: ANDERSON COSTA CARAPETA | T70: PAULO ABILIO QUEIROZ | U70: VIRTUAL CPS 3 | W70: 1
C71: 01/06/2026 | D71: AGS | G71: LUCYARA SIQUEIRA | I71: DOCUMENTAÇÃO EM ANÁLISE | J71: SP INT 4 | K71: 3 | M71: 01/02/2026 | N71: SP INT 4 | O71: GUSTAVO PAULINO SILVA | P71: 5 | Q71: 4 | R71: jan/2026 | S71: ANDERSON KUBICA | T71: GABRIEL MACIEL RETAMEIRO | U71: IMOB BOTUCATU | V71: IMOBILIARIA SILVA BOTUCATU | W71: 15
C72: 01/06/2026 | D72: AGS | G72: LUCYARA SIQUEIRA | I72: CPF ANALISADO | J72: SP INT 4 | K72: 3 | M72: 01/02/2026 | N72: SP INT 4 | O72: JAYRANE CAROLINE MARTINS FERRARI | P72: 17 | Q72: 6 | R72: jan/2026 | S72: ANDERSON KUBICA | T72: GABRIEL MACIEL RETAMEIRO | U72: IMOB BOTUCATU | V72: MTZ LANCAMENTOS IMOBILIARIOS | W72: 1
C73: 01/06/2026 | D73: AGS | G73: LUCYARA SIQUEIRA | I73: CPF APROVADO | J73: SP INT 4 | K73: 2 | M73: 01/02/2026 | N73: SP INT 4 | O73: JULIANO MARQUES VALENTE | P73: 4 | Q73: 1 | R73: jan/2026 | S73: ANDERSON KUBICA | T73: GABRIEL MACIEL RETAMEIRO | U73: IMOB BOTUCATU | V73: OASIS SOLUCOES E INTELIGENCIA IMOBILIARIA | W73: 2
C74: 01/06/2026 | D74: AGS | G74: LUCYARA SIQUEIRA | I74: CPF CONDICIONADO | J74: SP INT 4 | K74: 1 | M74: 01/02/2026 | N74: SP INT 4 | O74: REBECA PEREIRA BONFIM DA SILVA | P74: 2 | Q74: 2 | R74: jan/2026 | S74: ANDERSON KUBICA | T74: LARISSA DE SA MARQUES | U74: IMOB MARÍLIA | V74: BROKERS SOLUCOES IMOBILIARIAS | W74: 5
C75: 01/06/2026 | D75: AGS | G75: LUCYARA SIQUEIRA | I75: CONTRATO GERADO | J75: SP INT 4 | K75: 2 | M75: 01/02/2026 | N75: SP INT 4 | O75: TIAGO ALVES CARVALHO COELHO | P75: 15 | Q75: 6 | R75: jan/2026 | S75: ANDERSON KUBICA | T75: LARISSA DE SA MARQUES | U75: IMOB MARÍLIA | V75: ELEVARE NEGOCIOS IMOBILIARIOS | W75: 1
C76: 01/06/2026 | D76: AGS | G76: LUCYARA SIQUEIRA JACOB MARTINS | I76: CONTRATO ASSINADO | J76: SP INT 4 | K76: 1 | M76: 01/02/2026 | N76: SP INT 5 | O76: JEFERSON EDUARDO NUNES | P76: 19 | Q76: 15 | R76: jan/2026 | S76: ANDERSON KUBICA | T76: LARISSA DE SA MARQUES | U76: IMOB MARÍLIA | V76: LUPAX NEGOCIOS IMOBILIARIOS LTDA | W76: 1
C77: 01/06/2026 | D77: AGS | G77: LUCYARA SIQUEIRA JACOB MARTINS | I77: GANHO | J77: SP INT 4 | K77: 1 | M77: 01/02/2026 | N77: SP INT 5 | O77: JOEL TALMIR POPOWSKI | P77: 14 | Q77: 8 | R77: jan/2026 | S77: ANDERSON KUBICA | T77: LARISSA DE SA MARQUES | U77: IMOB MARÍLIA | V77: MORADAS SP | W77: 1
C78: 01/06/2026 | D78: AGS | G78: LUÍS FERNANDO CHAVES DA SILVA MOREIRA | I78: LEAD | J78: SP INT 4 | K78: 21 | M78: 01/02/2026 | N78: SP INT 5 | O78: JULIO CESAR FERREIRA | P78: 20 | Q78: 9 | R78: jan/2026 | S78: ANDERSON KUBICA | T78: LARISSA DE SA MARQUES | U78: IMOB MARÍLIA | V78: VINTTE NEGÓCIOS IMOBILIÁRIOS LTDA | W78: 1
C79: 01/06/2026 | D79: AGS | G79: LUÍS FERNANDO CHAVES DA SILVA MOREIRA | I79: DOCUMENTAÇÃO ENVIADA | J79: SP INT 4 | K79: 2 | M79: 01/02/2026 | N79: SP INT 5 | O79: THIAGO VIEIRA PROCOPIO | P79: 6 | Q79: 5 | R79: jan/2026 | S79: ANDERSON KUBICA | T79: NATHALIE FERNANDA POMPIANO | U79: IMOB BAURU | V79: MORADIAPAULISTA NEGOCIOS IMOBILIARIOS | W79: 1
C80: 01/06/2026 | D80: AGS | G80: LUÍS FERNANDO CHAVES DA SILVA MOREIRA | I80: DOCUMENTAÇÃO EM ANÁLISE | J80: SP INT 4 | K80: 2 | M80: 01/02/2026 | N80: SP INT 5 | O80: WELLINGTON DAMIAO CATARUSSI | P80: 11 | Q80: 10 | R80: jan/2026 | S80: ANDERSON KUBICA | T80: NATHALIE FERNANDA POMPIANO | U80: IMOB BAURU | V80: PASCHOARELLI IMOVEIS | W80: 1
C81: 01/06/2026 | D81: AGS | G81: LUÍS FERNANDO CHAVES DA SILVA MOREIRA | I81: CPF ANALISADO | J81: SP INT 4 | K81: 2 | M81: 01/02/2026 | N81: SP INT 6 | O81: ALEXANDRE FORMIGA NETO | P81: 10 | Q81: 1 | R81: jan/2026 | S81: ANDERSON KUBICA | T81: RONIE SANTIAGO DA SILVA | U81: LOJA IMOB BAURU 2 | V81: GRIZONI IMOBILIARIA | W81: 1
C82: 01/06/2026 | D82: AGS | G82: LUÍS FERNANDO CHAVES DA SILVA MOREIRA | I82: CPF APROVADO | J82: SP INT 4 | K82: 2 | M82: 01/02/2026 | N82: SP INT 6 | O82: ANDREA CRISTINA MATHEUS FRATI | P82: 7 | Q82: 5 | R82: jan/2026 | S82: ANDERSON KUBICA | T82: RONIE SANTIAGO DA SILVA | U82: LOJA IMOB BAURU 2 | V82: MJR CONSULTORIA IMOBILIARIA | W82: 1
C83: 01/06/2026 | D83: AGS | G83: LUÍS FERNANDO CHAVES DA SILVA MOREIRA | I83: CONTRATO GERADO | J83: SP INT 4 | K83: 3 | M83: 01/02/2026 | N83: SP INT 6 | O83: JACKSON DE ALMEIDA PIRES | P83: 14 | Q83: 12 | R83: jan/2026 | S83: ANDREA CRISTINA MATHEUS FRATI | T83: CARLOS ROBERTO DE OLIVEIRA FILHO | U83: HIBRIDA CREDENCIADA SOROCABA 2 | W83: 2
C84: 01/06/2026 | D84: AGS | G84: LUÍS FERNANDO CHAVES DA SILVA MOREIRA | I84: CONTRATO ASSINADO | J84: SP INT 4 | K84: 2 | M84: 01/02/2026 | N84: SP INT 6 | O84: MARCONE DA SILVA FERREIRA DE ANDRADE | P84: 10 | Q84: 7 | R84: jan/2026 | S84: ARMANDO DONIZETTI CUSTODIO | T84: BRUNO VINICIUS NEVES DA SILVA | U84: HIBRIDA CREDENCIADA LIMEIRA 1 | W84: 2
C85: 01/06/2026 | D85: AGS | G85: LUÍS FERNANDO CHAVES DA SILVA MOREIRA | I85: GANHO | J85: SP INT 4 | K85: 1 | M85: 01/02/2026 | N85: SP INT 6 | O85: PHILLIPE CAMILLOTI GRACIANO | P85: 25 | Q85: 13 | R85: jan/2026 | S85: ARMANDO DONIZETTI CUSTODIO | T85: CARLOS ALBERTO SOARES | U85: HIBRIDA CREDENCIADA LIMEIRA 1 | W85: 1
C86: 01/06/2026 | D86: AGS | G86: PAULA CRISTINA RASO MATTOS | I86: GANHO | J86: SP INT 4 | K86: 1 | M86: 01/02/2026 | N86: SP INT 6 | O86: VANESSA CRISTINE PERES | P86: 12 | Q86: 7 | R86: jan/2026 | S86: ARMANDO DONIZETTI CUSTODIO | T86: CICERO FERREIRA DA SILVA | U86: HIBRIDA CREDENCIADA LIMEIRA 1 | W86: 2
C87: 01/06/2026 | D87: AGS | G87: RAFAEL FERNANDES DECHICHI | I87: LEAD | J87: SP INT 4 | K87: 410 | M87: 01/03/2026 | N87: SENSIA CP | O87: BARBARA FERRARI | P87: 17 | Q87: 13 | R87: jan/2026 | S87: ARMANDO DONIZETTI CUSTODIO | T87: GABRIELA MARTINHO BARBOZA | U87: HIBRIDA CREDENCIADA LIMEIRA 1 | W87: 1
C88: 01/06/2026 | D88: AGS | G88: TATIANE ALVES PEREIRA | I88: LEAD | J88: SP INT 3 | K88: 10 | M88: 01/03/2026 | N88: SENSIA RP | O88: DOUGLAS MENDES DE AGUIAR RODRIGUES | P88: 14 | Q88: 7 | R88: jan/2026 | S88: BRENDA MANTOVANI CONTE | T88: CAMILA LEMOS GUIMARAES | U88: IMOB SOROCABA 3 | V88: CRIS ALMEIDA NEGOCIOS IMOBILIARIOS LTDA | W88: 1
C89: 01/06/2026 | D89: AGS | G89: TATIANE ALVES PEREIRA | I89: GANHO | J89: SP INT 3 | K89: 1 | M89: 01/03/2026 | N89: SP INT 1 | P89: 1 | Q89: 1 | R89: jan/2026 | S89: BRENDA MANTOVANI CONTE | T89: CAMILA LEMOS GUIMARAES | U89: IMOB SOROCABA 3 | V89: DUARCON ASSESSORIA IMOBILIARIA E CONSTRUTORA LTDA | W89: 1
C90: 01/06/2026 | D90: AGS | E90: GUSTAVO PAULINO SILVA | G90: GIOVANA KARINE TOLEDO VENTURA | I90: LEAD | J90: SP INT 4 | K90: 1 | M90: 01/03/2026 | N90: SP INT 1 | O90: ALEXANDRE MIRANDA DOS PASSOS | P90: 22 | Q90: 7 | R90: jan/2026 | S90: BRENDA MANTOVANI CONTE | T90: CAMILA LEMOS GUIMARAES | U90: IMOB SOROCABA 3 | V90: FABIO AUGUSTO BELLO IMOVEIS LTDA | W90: 1
C91: 01/06/2026 | D91: AGS | E91: GUSTAVO PAULINO SILVA | G91: GIOVANA KARINE TOLEDO VENTURA | I91: DOCUMENTAÇÃO ENVIADA | J91: SP INT 4 | K91: 1 | M91: 01/03/2026 | N91: SP INT 1 | O91: ANDERSON COSTA CARAPETA | P91: 16 | Q91: 8 | R91: jan/2026 | S91: BRENDA MANTOVANI CONTE | T91: CAMILA LEMOS GUIMARAES | U91: IMOB SOROCABA 3 | V91: FONTE IMOVEIS SOROCABA LTDA | W91: 1
C92: 01/06/2026 | D92: AGS | E92: GUSTAVO PAULINO SILVA | G92: GIOVANA KARINE TOLEDO VENTURA | I92: DOCUMENTAÇÃO EM ANÁLISE | J92: SP INT 4 | K92: 1 | M92: 01/03/2026 | N92: SP INT 1 | O92: DANIEL FAJARDO MONTANHANA | P92: 12 | Q92: 6 | R92: jan/2026 | S92: BRENDA MANTOVANI CONTE | T92: CAMILA LEMOS GUIMARAES | U92: IMOB SOROCABA 3 | V92: LRE IMOVEIS LTDA | W92: 1
C93: 01/06/2026 | D93: AGS | E93: GUSTAVO PAULINO SILVA | G93: GIOVANA KARINE TOLEDO VENTURA | I93: CPF ANALISADO | J93: SP INT 4 | K93: 1 | M93: 01/03/2026 | N93: SP INT 1 | O93: DANIELE DE CARVALHO | P93: 6 | Q93: 4 | R93: jan/2026 | S93: BRENDA MANTOVANI CONTE | T93: CAMILA LEMOS GUIMARAES | U93: IMOB SOROCABA 3 | V93: MBL PRIME SOLUÇÕES IMOBILIÁRIAS LTDA | W93: 3
C94: 01/06/2026 | D94: AGS | E94: GUSTAVO PAULINO SILVA | G94: GIOVANA KARINE TOLEDO VENTURA | I94: CPF CONDICIONADO | J94: SP INT 4 | K94: 1 | M94: 01/03/2026 | N94: SP INT 1 | O94: EVANDRO DE BRITO | P94: 22 | Q94: 10 | R94: jan/2026 | S94: BRENDA MANTOVANI CONTE | T94: CAMILA LEMOS GUIMARAES | U94: IMOB SOROCABA 3 | V94: META BROKERS IMÓVEIS LTDA | W94: 1
C95: 01/06/2026 | D95: AGS | E95: GUSTAVO PAULINO SILVA | G95: GIOVANA KARINE TOLEDO VENTURA | I95: CONTRATO GERADO | J95: SP INT 4 | K95: 1 | M95: 01/03/2026 | N95: SP INT 1 | O95: FABIO HENRIQUE VIDOTTI FERREIRA | P95: 7 | Q95: 3 | R95: jan/2026 | S95: BRENDA MANTOVANI CONTE | T95: CAMILA LEMOS GUIMARAES | U95: IMOB SOROCABA 3 | V95: MEU IMOVEL CERTO LTDA | W95: 1
C96: 01/06/2026 | D96: AGS | E96: GUSTAVO PAULINO SILVA | G96: GIOVANA KARINE TOLEDO VENTURA | I96: CONTRATO ASSINADO | J96: SP INT 4 | K96: 1 | M96: 01/03/2026 | N96: SP INT 1 | O96: PABLO MEDEIROS DA SILVA GADELHA | P96: 22 | Q96: 15 | R96: jan/2026 | S96: BRENDA MANTOVANI CONTE | T96: CAMILA LEMOS GUIMARAES | U96: IMOB SOROCABA 3 | V96: REIS E GONZALEZ NEGOCIOS IMOBILIARIOS LTDA | W96: 1
C97: 01/06/2026 | D97: AGS | E97: GUSTAVO PAULINO SILVA | G97: GIOVANA KARINE TOLEDO VENTURA | I97: GANHO | J97: SP INT 4 | K97: 1 | M97: 01/03/2026 | N97: SP INT 1 | O97: TIAGO AUGUSTO DA COSTA | P97: 20 | Q97: 5 | R97: jan/2026 | S97: BRENDA MANTOVANI CONTE | T97: CAMILA LEMOS GUIMARAES | U97: IMOB SOROCABA 3 | V97: RODRIGUES E OLIVEIRA NEGÓCIOS IMOBILIÁRIOS LTDA | W97: 2
C98: 01/06/2026 | D98: AGS | E98: GUSTAVO PAULINO SILVA | G98: GUSTAVO PAULINO SILVA | I98: LEAD | J98: SP INT 4 | K98: 1 | M98: 01/03/2026 | N98: SP INT 2 | O98: DOMINIQUE DAMASO DE SALES | P98: 17 | Q98: 11 | R98: jan/2026 | S98: BRENDA MANTOVANI CONTE | T98: DOUGLAS OLIVEIRA CONCEICAO | U98: IMOB SOROCABA 2 | V98: BPONTO IMOVEIS LTDA | W98: 1
C99: 01/06/2026 | D99: AGS | E99: GUSTAVO PAULINO SILVA | G99: MARISA CRISTINA VIEIRA | I99: GANHO | J99: SP INT 4 | K99: 1 | M99: 01/03/2026 | N99: SP INT 2 | O99: FLAVIANO DE SOUZA CORREA | P99: 13 | Q99: 4 | R99: jan/2026 | S99: BRENDA MANTOVANI CONTE | T99: DOUGLAS OLIVEIRA CONCEICAO | U99: IMOB SOROCABA 2 | V99: FAMILY NEGOCIOS IMOBILIARIOS | W99: 1
C100: 01/06/2026 | D100: AGS | E100: HEITOR NEVES MANCUZO | G100: HECTOR GIULIANO MENEGHETTI FERREIRA | I100: REPASSE | J100: SP INT 2 | K100: 1 | M100: 01/03/2026 | N100: SP INT 2 | O100: HEITOR NEVES MANCUZO | P100: 20 | Q100: 11 | R100: jan/2026 | S100: BRENDA MANTOVANI CONTE | T100: DOUGLAS OLIVEIRA CONCEICAO | U100: IMOB SOROCABA 2 | V100: MVR ASSESSORIA IMOBILIARIA LTDA | W100: 1
C101: 01/06/2026 | D101: AGS | E101: HEITOR NEVES MANCUZO | G101: HECTOR GIULIANO MENEGHETTI FERREIRA | I101: REGISTRO | J101: SP INT 2 | K101: 1 | M101: 01/03/2026 | N101: SP INT 2 | O101: JEFERSON CRISTIANO REGHINI | P101: 14 | Q101: 10 | R101: jan/2026 | S101: BRENDA MANTOVANI CONTE | T101: DOUGLAS OLIVEIRA CONCEICAO | U101: IMOB SOROCABA 2 | V101: SOLO CONSULTORES IMOBILIARIOS LTDA | W101: 1
... C103: 01/06/2026 | D103: AGS | E103: PHILLIPE CAMILLOTI GRACIANO | G103: MICHELLE RADAEL | I103: LEAD | J103: SP INT 6 | K103: 1 | M103: 01/03/2026 | N103: SP INT 2 | O103: STEPHANE MASCARENHAS TEIXEIRA | P103: 18 | Q103: 15 | R103: jan/2026 | S103: BRENDA MANTOVANI CONTE | T103: JANINE SILVA GODOY | U103: IMOB ITU 1 | V103: FIRST HOUSE BROKERS | W103: 1
C104: 01/06/2026 | D104: AGS | E104: PHILLIPE CAMILLOTI GRACIANO | G104: MICHELLE RADAEL | I104: DOCUMENTAÇÃO ENVIADA | J104: SP INT 6 | K104: 1 | M104: 01/03/2026 | N104: SP INT 3 | P104: 1 | Q104: 1 | R104: jan/2026 | S104: BRENDA MANTOVANI CONTE | T104: JANINE SILVA GODOY | U104: IMOB ITU 1 | V104: FIVEH SOLUCOES IMOBILIARIAS | W104: 1
C105: 01/06/2026 | D105: AGS | E105: PHILLIPE CAMILLOTI GRACIANO | G105: PAULA ROBERTA DE SOUSA | I105: LEAD | J105: SP INT 6 | K105: 1 | M105: 01/03/2026 | N105: SP INT 3 | O105: ARMANDO DONIZETTI CUSTODIO | P105: 17 | Q105: 14 | R105: jan/2026 | S105: BRENDA MANTOVANI CONTE | T105: JANINE SILVA GODOY | U105: IMOB ITU 1 | V105: TIGGO NEGOCIOS IMOBILIARIOS LTDA ME | W105: 1
C106: 01/06/2026 | D106: AGS | E106: PHILLIPE CAMILLOTI GRACIANO | G106: ROSELI GORETI DOS REIS | I106: DOCUMENTAÇÃO ENVIADA | J106: SP INT 6 | K106: 1 | M106: 01/03/2026 | N106: SP INT 3 | O106: BRUNA PAULINO BENEDETTI | P106: 12 | Q106: 10 | R106: jan/2026 | S106: BRENDA MANTOVANI CONTE | T106: JHULYANNE ALLYNE ADAO MAZIERE | U106: IMOB SOROCABA | V106: ALINE JANETE LUCIO DA SILVA NEGOCIOS IMOBILIARIOS LTDA | W106: 1
C107: 01/06/2026 | D107: AGS | E107: PHILLIPE CAMILLOTI GRACIANO | G107: ROSELI GORETI DOS REIS | I107: DOCUMENTAÇÃO EM ANÁLISE | J107: SP INT 6 | K107: 1 | M107: 01/03/2026 | N107: SP INT 3 | O107: DEIVES RODRIGO DA COSTA | P107: 25 | Q107: 14 | R107: jan/2026 | S107: BRENDA MANTOVANI CONTE | T107: JHULYANNE ALLYNE ADAO MAZIERE | U107: IMOB SOROCABA | V107: DEBORA BORGES EMPREENDIMENTOS IMOBILIARIOS - ME | W107: 1
C108: 01/06/2026 | D108: AGS | E108: PHILLIPE CAMILLOTI GRACIANO | G108: ROSELI GORETI DOS REIS | I108: CPF ANALISADO | J108: SP INT 6 | K108: 1 | M108: 01/03/2026 | N108: SP INT 3 | O108: MAISA MUNIZ DA SILVA | P108: 13 | Q108: 8 | R108: jan/2026 | S108: BRENDA MANTOVANI CONTE | T108: JHULYANNE ALLYNE ADAO MAZIERE | U108: IMOB SOROCABA | V108: FONTE IMOVEIS SOROCABA LTDA | W108: 1
C109: 01/06/2026 | D109: AGS | E109: PHILLIPE CAMILLOTI GRACIANO | G109: ROSELI GORETI DOS REIS | I109: CPF CONDICIONADO | J109: SP INT 6 | K109: 1 | M109: 01/03/2026 | N109: SP INT 3 | O109: PEDRO MORENO MARQUES | P109: 15 | Q109: 7 | R109: jan/2026 | S109: BRENDA MANTOVANI CONTE | T109: JHULYANNE ALLYNE ADAO MAZIERE | U109: IMOB SOROCABA | V109: MARTINS PRIME IMOVES LTDA | W109: 1
C110: 01/06/2026 | D110: HOUSE | G110: ANDRIELLI DO PRADO MACHADO | I110: LEAD | J110: SP INT 6 | K110: 3 | M110: 01/03/2026 | N110: SP INT 3 | O110: THAYNA LAIS DA SILVA | P110: 12 | Q110: 7 | R110: jan/2026 | S110: BRENDA MANTOVANI CONTE | T110: JHULYANNE ALLYNE ADAO MAZIERE | U110: IMOB SOROCABA | V110: NN CONSULTORIA IMOBILIARIA SOROCABA LTDA | W110: 1
C111: 01/06/2026 | D111: HOUSE | G111: DAVI GABRIEL DE AVILA SIQUEIRA | I111: LEAD | J111: SP INT 6 | K111: 1 | M111: 01/03/2026 | N111: SP INT 4 | O111: ADALTON JOSE DA SILVA | P111: 16 | Q111: 6 | R111: jan/2026 | S111: BRENDA MANTOVANI CONTE | T111: JHULYANNE ALLYNE ADAO MAZIERE | U111: IMOB SOROCABA | V111: RAFAEL WINCLER IMOVEIS LTDA | W111: 1
C112: 01/06/2026 | D112: HOUSE | G112: DAYANE ROBERTA ALVES | I112: REGISTRO | J112: SP INT 5 | K112: 1 | M112: 01/03/2026 | N112: SP INT 4 | O112: DAIANE CRISTINA JIRICO | P112: 25 | Q112: 16 | R112: jan/2026 | S112: BRUNA PAULINO BENEDETTI | T112: SABRINA CRISTINA DIAS CYRINO | U112: LOJA VIRTUAL SAO CARLOS 02 | W112: 2
...

Sheet Planilha2
U1: regionalcompleta | V1: (Vários itens)
A2: diretoria | B2: DIRETORIA SPI | E2: diretoria | F2: DIRETORIA SPI | U2: diretoria | V2: DIRETORIA SPI
A3: canal_loja | B3: HOUSE | E3: canal_loja | F3: IMOB | U3: canal_loja | V3: IMOB
A4: data_base | B4: 01/04/2026 | E4: data_base | F4: 01/04/2026 | U4: data_base | V4: 01/03/2026
A5: dia | B5: (Vários itens) | E5: dia | F5: (Vários itens) | U5: dia | V5: All
A7: Regional | B7: Equipe House | C7: CPF Anl. | G7: CPF Anl. | U7: nom_loja | V7: supervisor_imob | W7: regional | X7: status_funil | Y7: Funil_Real
G17: CPF Anl.
E18: SP INT 1 | F18: LARISSA NEVES TEIXEIRA | G18: 7
E19: SP INT 2 | F19: HENRIQUE NEVES GARBELLINI | G19: 9 | M19: CPF Anl. | R19: Qtd_CPF_Analisado
E20: SP INT 3 | F20: LUCIANO FERREIRA DA SILVA | G20: 3 | K20: SP INT 1 | L20: ANDERSON COSTA CARAPETA | M20: 4 | P20: SP INT 1 | Q20: LARISSA NEVES TEIXEIRA | R20: 6
E21: SP INT 4 | F21: GABRIEL MACIEL RETAMEIRO | G21: 3 | K21: SP INT 2 | L21: FLAVIANO DE SOUZA CORREA | M21: 3 | P21: SP INT 2 | Q21: HENRIQUE NEVES GARBELLINI | R21: 19
E22: SP INT 5 | F22: RODRIGO MONTEIRO DE LIMA | G22: 1 | K22: SP INT 3 | P22: SP INT 3 | Q22: CAMILA MENDES FRANCISCO | R22: 6
E23: SP INT 6 | F23: CAMILA LEMOS GUIMARAES | G23: 3 | K23: SP INT 4 | L23: TIAGO ALVES CARVALHO COELHO | M23: 6 | P23: SP INT 4 | Q23: GABRIEL MACIEL RETAMEIRO | R23: 8
K24: SP INT 5 | L24: JEFERSON EDUARDO NUNES | M24: 4 | P24: SP INT 5 | Q24: VANESSA FERREIRA DE MORAES | R24: 4
K25: SP INT 6 | L25: JACKSON DE ALMEIDA PIRES | M25: 4 | P25: SP INT 6 | Q25: CAMILA LEMOS GUIMARAES | R25: 8

Sheet Planilha1
B1: Todos | C1: SPI | E1: Definitivos | F1: SPI | H1: Supervisor | I1: SPI
B2: {=_xlfn.UNIQUE('TD Painel'!#REF!)} -> #REF! | C2: =_xlfn.XLOOKUP(Planilha1!B2,'TD Painel'!#REF!,'TD Painel'!#REF!) -> #REF! | E2: HENRIQUE NEVES GARBELLINI | F2: SP INT 2 | H2: {=_xlfn._xlws.FILTER(_xlfn.ANCHORARRAY(B2), COUNTIF(E2:E30,_xlfn.ANCHORARRAY(B2)) = 0)} -> #REF! | I2: =_xlfn.XLOOKUP(H2,B:B,C:C) -> #REF!
C3: =_xlfn.XLOOKUP(Planilha1!B3,'TD Painel'!#REF!,'TD Painel'!#REF!) -> #REF! | E3: CAMILA REGINA MELCHIADES | F3: SP INT 2 | I3: =_xlfn.XLOOKUP(H3,B:B,C:C) -> #REF!
C4: =_xlfn.XLOOKUP(Planilha1!B4,'TD Painel'!#REF!,'TD Painel'!#REF!) -> #REF! | E4: VINICIUS VIEIRA FRANCISCO | F4: SP INT 4 | I4: =_xlfn.XLOOKUP(H4,B:B,C:C) -> #REF!
C5: =_xlfn.XLOOKUP(Planilha1!B5,'TD Painel'!#REF!,'TD Painel'!#REF!) -> #REF! | E5: LUCAS PEREIRA MIGUEL | F5: SP INT 2 | I5: =_xlfn.XLOOKUP(H5,B:B,C:C) -> #REF!
C6: =_xlfn.XLOOKUP(Planilha1!B6,'TD Painel'!#REF!,'TD Painel'!#REF!) -> #REF! | E6: CAMILA MENDES FRANCISCO | F6: SP INT 3 | I6: =_xlfn.XLOOKUP(H6,B:B,C:C) -> #REF!
C7: =_xlfn.XLOOKUP(Planilha1!B7,'TD Painel'!#REF!,'TD Painel'!#REF!) -> #REF! | E7: CAMILA LEMOS GUIMARAES | F7: SP INT 6 | I7: =_xlfn.XLOOKUP(H7,B:B,C:C) -> #REF!
C8: =_xlfn.XLOOKUP(Planilha1!B8,'TD Painel'!#REF!,'TD Painel'!#REF!) -> #REF! | E8: JANINE SILVA GODOY | F8: SP INT 6 | I8: =_xlfn.XLOOKUP(H8,B:B,C:C) -> #REF!
C9: =_xlfn.XLOOKUP(Planilha1!B9,'TD Painel'!#REF!,'TD Painel'!#REF!) -> #REF! | E9: JHULYANNE ALLYNE ADAO MAZIERE | F9: SP INT 6 | I9: =_xlfn.XLOOKUP(H9,B:B,C:C) -> #REF!
C10: =_xlfn.XLOOKUP(Planilha1!B10,'TD Painel'!#REF!,'TD Painel'!#REF!) -> #REF! | E10: ANA LETICIA COTRIM ALONSO | F10: SP INT 3 | I10: =_xlfn.XLOOKUP(H10,B:B,C:C) -> #REF!
C11: =_xlfn.XLOOKUP(Planilha1!B11,'TD Painel'!#REF!,'TD Painel'!#REF!) -> #REF! | E11: WANDERSON FERNANDO ALVES JUNIOR | F11: SP INT 3 | I11: =_xlfn.XLOOKUP(H11,B:B,C:C) -> #REF!
C12: =_xlfn.XLOOKUP(Planilha1!B12,'TD Painel'!#REF!,'TD Painel'!#REF!) -> #REF! | E12: GUSTAVO GUINATTI VENTURINI | F12: SP INT 1 | I12: =_xlfn.XLOOKUP(H12,B:B,C:C) -> #REF!
C13: =_xlfn.XLOOKUP(Planilha1!B13,'TD Painel'!#REF!,'TD Painel'!#REF!) -> #REF! | E13: ALINE RODRIGUES DA SILVA | F13: SP INT 5 | I13: =_xlfn.XLOOKUP(H13,B:B,C:C) -> #REF!
C14: =_xlfn.XLOOKUP(Planilha1!B14,'TD Painel'!#REF!,'TD Painel'!#REF!) -> #REF! | E14: RODRIGO PERES BORBA | F14: SP INT 1 | I14: =_xlfn.XLOOKUP(H14,B:B,C:C) -> #REF!
... C30: =_xlfn.XLOOKUP(Planilha1!B30,'TD Painel'!#REF!,'TD Painel'!#REF!) -> #REF! | E30: ARTHUR TEIXEIRA PEREIRA | F30: SP INT 4 | I30: =_xlfn.XLOOKUP(H30,B:B,C:C) -> #REF!
C31: =_xlfn.XLOOKUP(Planilha1!B31,'TD Painel'!#REF!,'TD Painel'!#REF!) -> #REF! | I31: =_xlfn.XLOOKUP(H31,B:B,C:C) -> #REF!
C32: =_xlfn.XLOOKUP(Planilha1!B32,'TD Painel'!#REF!,'TD Painel'!#REF!) -> #REF! | I32: =_xlfn.XLOOKUP(H32,B:B,C:C) -> #REF!
C33: =_xlfn.XLOOKUP(Planilha1!B33,'TD Painel'!#REF!,'TD Painel'!#REF!) -> #REF! | I33: =_xlfn.XLOOKUP(H33,B:B,C:C) -> #REF!
C34: =_xlfn.XLOOKUP(Planilha1!B34,'TD Painel'!#REF!,'TD Painel'!#REF!) -> #REF! | I34: =_xlfn.XLOOKUP(H34,B:B,C:C) -> #REF!
C35: =_xlfn.XLOOKUP(Planilha1!B35,'TD Painel'!#REF!,'TD Painel'!#REF!) -> #REF! | I35: =_xlfn.XLOOKUP(H35,B:B,C:C) -> #REF!
C36: =_xlfn.XLOOKUP(Planilha1!B36,'TD Painel'!#REF!,'TD Painel'!#REF!) -> #REF! | I36: =_xlfn.XLOOKUP(H36,B:B,C:C) -> #REF!
C37: =_xlfn.XLOOKUP(Planilha1!B37,'TD Painel'!#REF!,'TD Painel'!#REF!) -> #REF! | I37: =_xlfn.XLOOKUP(H37,B:B,C:C) -> #REF!
C38: =_xlfn.XLOOKUP(Planilha1!B38,'TD Painel'!#REF!,'TD Painel'!#REF!) -> #REF! | I38: =_xlfn.XLOOKUP(H38,B:B,C:C) -> #REF!
C39: =_xlfn.XLOOKUP(Planilha1!B39,'TD Painel'!#REF!,'TD Painel'!#REF!) -> #REF! | I39: =_xlfn.XLOOKUP(H39,B:B,C:C) -> #REF!
C40: =_xlfn.XLOOKUP(Planilha1!B40,'TD Painel'!#REF!,'TD Painel'!#REF!) -> #REF! | I40: =_xlfn.XLOOKUP(H40,B:B,C:C) -> #REF!
C41: =_xlfn.XLOOKUP(Planilha1!B41,'TD Painel'!#REF!,'TD Painel'!#REF!) -> #REF! | I41: =_xlfn.XLOOKUP(H41,B:B,C:C) -> #REF!
C42: =_xlfn.XLOOKUP(Planilha1!B42,'TD Painel'!#REF!,'TD Painel'!#REF!) -> #REF! | I42: =_xlfn.XLOOKUP(H42,B:B,C:C) -> #REF!
... C86: =_xlfn.XLOOKUP(Planilha1!B86,'TD Painel'!#REF!,'TD Painel'!#REF!) -> #REF! | I86: =_xlfn.XLOOKUP(H86,B:B,C:C) -> #REF!
C87: =_xlfn.XLOOKUP(Planilha1!B87,'TD Painel'!#REF!,'TD Painel'!#REF!) -> #REF!
C88: =_xlfn.XLOOKUP(Planilha1!B88,'TD Painel'!#REF!,'TD Painel'!#REF!) -> #REF!
C89: =_xlfn.XLOOKUP(Planilha1!B89,'TD Painel'!#REF!,'TD Painel'!#REF!) -> #REF!
C90: =_xlfn.XLOOKUP(Planilha1!B90,'TD Painel'!#REF!,'TD Painel'!#REF!) -> #REF!
C91: =_xlfn.XLOOKUP(Planilha1!B91,'TD Painel'!#REF!,'TD Painel'!#REF!) -> #REF!
C92: =_xlfn.XLOOKUP(Planilha1!B92,'TD Painel'!#REF!,'TD Painel'!#REF!) -> #REF!
C93: =_xlfn.XLOOKUP(Planilha1!B93,'TD Painel'!#REF!,'TD Painel'!#REF!) -> #REF!
C94: =_xlfn.XLOOKUP(Planilha1!B94,'TD Painel'!#REF!,'TD Painel'!#REF!) -> #REF!
C95: =_xlfn.XLOOKUP(Planilha1!B95,'TD Painel'!#REF!,'TD Painel'!#REF!) -> #REF!
C96: =_xlfn.XLOOKUP(Planilha1!B96,'TD Painel'!#REF!,'TD Painel'!#REF!) -> #REF!
C97: =_xlfn.XLOOKUP(Planilha1!B97,'TD Painel'!#REF!,'TD Painel'!#REF!) -> #REF!
C98: =_xlfn.XLOOKUP(Planilha1!B98,'TD Painel'!#REF!,'TD Painel'!#REF!) -> #REF!
... C115: =_xlfn.XLOOKUP(Planilha1!B115,'TD Painel'!#REF!,'TD Painel'!#REF!) -> #REF!
